<Properties>
  <MonoDevelop.Ide.DebuggingService.Breakpoints>
    <BreakpointStore />
  </MonoDevelop.Ide.DebuggingService.Breakpoints>
  <MultiItemStartupConfigurations />
  <MonoDevelop.Ide.Workbench ActiveDocument="Agency.Data/DbContextAgency.cs">
    <Files>
      <File FileName="Agency.Data/Entities/User.cs" Line="16" Column="1" />
      <File FileName="Agency.Data/DbContextAgency.cs" Line="5" Column="29" />
    </Files>
    <Pads>
      <Pad Id="ProjectPad">
        <State name="__root__">
          <Node name="Agency.Data" expanded="True">
            <Node name="Agency.Data" expanded="True">
              <Node name="Entities" expanded="True" />
              <Node name="DbContextAgency.cs" selected="True" />
            </Node>
          </Node>
        </State>
      </Pad>
    </Pads>
  </MonoDevelop.Ide.Workbench>
  <MonoDevelop.Ide.Workspace ActiveConfiguration="Debug" />
  <MonoDevelop.Ide.DebuggingService.PinnedWatches />
</Properties>